grepper_python/__init__.py
grepper_python/answer.py
grepper_python/exceptions.py
grepper_python/main.py
tests/__init__.py
tests/test_fetch_answer.py
tests/test_search.py
tests/test_update_answer.py
grepper_python-0.0.1a0.dist-info/LICENSE
grepper_python-0.0.1a0.dist-info/METADATA
grepper_python-0.0.1a0.dist-info/WHEEL
grepper_python-0.0.1a0.dist-info/top_level.txt
grepper_python-0.0.1a0.dist-info/RECORD
