Metadata-Version: 2.1
Name: grepper-python
Version: 0.0.1a0
Summary: An API wrapper for the Grepper API.
Home-page: https://github.com/CodeGrepper/grepper-python
Author: CodedGrepper
Author-email: support@grepper.com
Classifier: Programming Language :: Python :: 3
Requires-Python: >=3.7
License-File: LICENSE
Requires-Dist: requests
Requires-Dist: urllib3
